AUTHORS.rst
CONTRIBUTING.rst
HISTORY.rst
LICENSE
MANIFEST.in
README.rst
setup.cfg
setup.py
djangocms_twitter/__init__.py
djangocms_twitter/cms_plugins.py
djangocms_twitter/conf.py
djangocms_twitter/forms.py
djangocms_twitter/models.py
djangocms_twitter/migrations/0001_initial.py
djangocms_twitter/migrations/__init__.py
djangocms_twitter/south_migrations/0001_initial.py
djangocms_twitter/south_migrations/__init__.py
djangocms_twitter/static/css/djangocms_twitter/djangocms_twitter.css
djangocms_twitter/static/img/djangocms_twitter/twitter.png
djangocms_twitter/static/js/djangocms_twitter/djangocms_twitter.js
djangocms_twitter/static/js/djangocms_twitter/admin/djangocms_twitter.js
djangocms_twitter/templates/djangocms_twitter/default.html
djangocms_twitter/templatetags/__init__.py
djangocms_twitter/templatetags/djangocms_twitter.py
djangocms_twitter2.egg-info/PKG-INFO
djangocms_twitter2.egg-info/SOURCES.txt
djangocms_twitter2.egg-info/dependency_links.txt
djangocms_twitter2.egg-info/not-zip-safe
djangocms_twitter2.egg-info/requires.txt
djangocms_twitter2.egg-info/top_level.txt