Metadata-Version: 1.1
Name: djangocms-twitter2
Version: 0.1.0
Summary: The easiest way to display tweets for your django-cms powered site, using the latest Twitter 1.1 API. It's a great option for embedding tweets on your site without third-party widgets.
Home-page: https://github.com/mishbahr/djangocms-twitter2
Author: Mishbah Razzaque
Author-email: mishbahx@gmail.com
License: BSD
Keywords: djangocms-twitter2
Platform: UNKNOWN
Classifier: Development Status :: 2 - Pre-Alpha
Classifier: Framework :: Django
Classifier: Intended Audience :: Developers
Classifier: License :: OSI Approved :: BSD License
Classifier: Natural Language :: English
Classifier: Programming Language :: Python :: 2
Classifier: Programming Language :: Python :: 2.6
Classifier: Programming Language :: Python :: 2.7
Classifier: Programming Language :: Python :: 3
Classifier: Programming Language :: Python :: 3.3
